setup.py
cxpegg/__init__.py
cxpegg/cxpegg.py
cxpegg.egg-info/PKG-INFO
cxpegg.egg-info/SOURCES.txt
cxpegg.egg-info/dependency_links.txt
cxpegg.egg-info/top_level.txt
cxpegg.egg-info/zip-safe